{
  "11": {
    "name": "Мебель",
    "primary_type_filters": [
      "подкатегория",
      "категория мебели",
      "подтип"
    ],
    "allowed_params": {
      "высота, мм": "number",
      "высота, см": "number",
      "длина спального места, см": "number",
      "длина, мм": "number",
      "длина, см": "number",
      "категория мебели": "string",
      "подкатегория": "string",
      "подтип": "string",
      "стиль": "string",
      "страна производства": "string",
      "цвет": "string",
      "ширина спального места, см": "number",
      "ширина, мм": "number",
      "ширина, см": "number",
      "материал": "string",
      "количество секций": "integer"
    }
  },
  "12": {
    "name": "Освещение",
    "primary_type_filters": [
      "тип",
      "подтип"
    ],
    "allowed_params": {
      "артикул производителя": "string",
      "бренд": "string",
      "вид ламп": "string",
      "возможность подключения диммера": "boolean",
      "высота, мм": "number",
      "диаметр": "number",
      "длина, мм": "number",
      "для натяжных потолков": "boolean",
      "для низких потолков": "boolean",
      "количество ламп": "integer",
      "количество плафонов/абажуров": "integer",
      "материал арматуры": "string",
      "материал плафона/абажура": "string",
      "место в интерьере": "string",
      "мощность лампы, w": "number",
      "направление абажуров/плафонов": "string",
      "напряжение": "string",
      "общая мощность, w": "number",
      "подтип": "string",
      "степень защиты (ip)": "string",
      "стиль": "string",
      "страна производства": "string",
      "тип": "string",
      "цвет арматуры": "string",
      "цвет плафона/абажура": "string",
      "цоколь": "string",
      "ширина, мм": "number"
    }
  }
}